torchstats/__init__.py
torchstats/as_integer.py
torchstats/bayesian_network.py
torchstats/categorical.py
torchstats/input_space.py
torchstats/mixture.py
torchstats/multivariate.py
torchstats/one_hot.py
torchstats/point_distribution.py
torchstats/probability_distribution.py
torchstats/uniform.py
torchstats/univariate.py
torchstats/utils.py
torchstats-0.1.0.dist-info/licenses/LICENSE
torchstats-0.1.0.dist-info/WHEEL
torchstats-0.1.0.dist-info/METADATA
torchstats-0.1.0.dist-info/RECORD
