Metadata-Version: 2.4
Name: torchstats
Version: 0.1.0
Summary: Statistical functions, mostly probability distributions, in PyTorch.
Author-email: David Boetius <david.boetius@uni-konstanz.de>
Requires-Python: >=3.10
Classifier: Programming Language :: Python :: 3
Classifier: License :: OSI Approved :: MIT License
License-File: LICENSE
Requires-Dist: torch>=1.12.1,<3.0
Requires-Dist: numpy>=1.25,<3.0
Requires-Dist: scipy>=1.11,<2.0
Requires-Dist: scikit-learn>=1.3.2,<2.0
Requires-Dist: rust_enum==1.1.5
Requires-Dist: torchstats[test, develop] ; extra == "all"
Requires-Dist: ruff==0.11.11 ; extra == "develop"
Requires-Dist: pytest>=7.4,<7.5 ; extra == "test"
Requires-Dist: nox==2025.5.1 ; extra == "test"
Provides-Extra: all
Provides-Extra: develop
Provides-Extra: test
